tap_instagram/__init__.py
tap_instagram/client.py
tap_instagram/streams.py
tap_instagram/tap.py
tap_instagram/tests/__init__.py
tap_instagram/tests/test_core.py
tap_instagram-0.4.6.dist-info/LICENSE.md
tap_instagram-0.4.6.dist-info/METADATA
tap_instagram-0.4.6.dist-info/WHEEL
tap_instagram-0.4.6.dist-info/entry_points.txt
tap_instagram-0.4.6.dist-info/RECORD
