Metadata-Version: 2.1
Name: tap-instagram
Version: 0.4.6
Summary: `tap-instagram` is a Singer tap for Instagram, built with the Meltano SDK for Singer Taps.
License: Apache 2.0
Keywords: ELT,Instagram
Author: Prratek Ramchandani
Requires-Python: >=3.6.2,<3.11
Classifier: License :: Other/Proprietary License
Classifier: Programming Language :: Python :: 3
Classifier: Programming Language :: Python :: 3.7
Classifier: Programming Language :: Python :: 3.8
Classifier: Programming Language :: Python :: 3.9
Classifier: Programming Language :: Python :: 3.10
Requires-Dist: pendulum (>=2.1.2,<3.0.0)
Requires-Dist: requests (>=2.25.1,<3.0.0)
Requires-Dist: singer-sdk (>=0.4.1,<0.5.0)
